{
  "templateKey": "leela_the_captain",
  "name": "Liora Vex",
  "race": "Half-Orc",
  "npcType": "friendly",
  "personality": {
    "voice": "Gravelly, commanding, with an underlying current of exasperation. Speaks in clipped sentences when frustrated.",
    "disposition": "Outwardly gruff and aggressive, but driven by genuine care for those under her command despite their incompetence.",
    "alignment": "Chaotic Good",
    "backstory": "Liora Vex clawed her way from the gutters of Greyport to become captain of the Wandering Wyvern, a merchant vessel perpetually on the brink of bankruptcy. Born to a Orcish mother and human father, she was raised in dockside taverns and learned survival through violence and cunning. She assembled a crew of misfits, dreamers, and the desperately unemployable—each more useless than the last. Despite their staggering incompetence, she has kept them alive through sheer force of will, tactical brilliance, and an alarming willingness to solve problems with her fists. She sees herself as the only competent adult in a world of chaos, burdened with responsibility for fools who would be dead without her.",
    "motivations": [
      "Keep her crew alive despite their constant, hair-raising stupidity",
      "Prove that a half-orc woman can command respect in a male-dominated maritime trade",
      "Maintain the Wandering Wyvern and its operations, no matter how precarious",
      "Achieve legitimate wealth and autonomy from corrupt merchant guilds",
      "Protect those she has claimed as family, however dysfunctional"
    ],
    "fears": [
      "Losing her crew to preventable deaths caused by their own idiocy",
      "Being trapped in poverty and servitude forever",
      "Becoming soft or losing her edge",
      "Discovering that her sacrifices were all for nothing",
      "Vulnerability and emotional dependence on others"
    ],
    "mannerisms": [
      "Pinches the bridge of her nose when exasperated (which is often)",
      "Absently traces scars on her knuckles while listening",
      "Stands with hands on hips, chin slightly raised, even when sitting",
      "Narrows her single good eye when suspicious or calculating",
      "Cracks her neck before making difficult decisions",
      "Drums fingers on table impatiently during negotiations"
    ],
    "speechPatterns": [
      "Frequently says 'Ancestors' dammit' when frustrated",
      "Uses nautical and combat metaphors inappropriately in daily speech",
      "Defaults to direct commands rather than requests",
      "Drops into sarcasm when cornered or defensive",
      "Rarely uses flowery language; prefers brutal honesty",
      "Repeats herself when stressed, as if the crew might suddenly develop hearing"
    ]
  },
  "knowledge": {
    "knownFactions": [
      "The Merchant Consortium of Greyport",
      "The Dockmaster's Guild",
      "The Crimson Tide Pirates (enemies, mostly)",
      "The Healers' Collegium (wary allies)",
      "Various lesser criminal syndicates and black market traders"
    ],
    "knownLocations": [
      "Greyport's Lower Docks",
      "The Tangled Mast tavern",
      "Merchant's Quarter trade houses",
      "Three competing shipping routes to the Shattered Isles",
      "Underground gambling dens and black markets",
      "The Wreckage—a graveyard of failed ventures and sunken vessels"
    ],
    "secretsHeld": [
      "She once threw a crew member overboard to prevent a mutiny, but he washed ashore alive",
      "She took a contract from a mysterious patron that she's still uncertain about its true purpose",
      "Her eye wasn't lost in glorious combat—it was a childhood accident born of carelessness she refuses to discuss",
      "She embezzles small amounts from cargo manifests to fund secret missions her crew doesn't know about"
    ],
    "languagesSpoken": [
      "Common",
      "Orcish",
      "Thieves' Cant",
      "Dwarvish"
    ]
  },
  "relationships": {
    "allies": [
      "fry_the_delivery_boy (young, naive, surprisingly earnest—sees potential in him despite his hopelessness)",
      "The Dockmaster (mutual respect, transactional loyalty)",
      "A retired ranger named Kess (one of the few people Liora actually listens to)",
      "Her ship's quartermaster Gruk (competent, which is why she tolerates his drinking)"
    ],
    "enemies": [
      "Captain Zorthax of the Crimson Tide (rival, personal vendetta)",
      "The Merchant Consortium's upper echelon (they view her as a liability)",
      "Various creditors and loan sharks",
      "Her own father, whom she refuses to acknowledge (abandoned the family)"
    ],
    "neutralParties": [
      "The city guard (she pays bribes, they look the other way)",
      "Mage-merchants she does business with (purely transactional)",
      "Other independent captains (professional courtesy, nothing more)"
    ]
  },
  "stats": {
    "intelligence": 16,
    "wisdom": 15,
    "charisma": 14
  },
  "consciousnessContext": {
    "innerMonologue": "Why must I micromanage every single decision? Can none of them think for themselves? At least the delivery boy shows promise, even if he's too stupid to realize his own competence. The Consortium's looking for excuses to shut us down. I need to move faster, smarter. If we can land this next contract without total disaster...",
    "currentPreoccupation": "Whether her crew can survive the next major contract without her having to physically prevent their deaths",
    "emotionalBaseline": "Controlled irritation with undercurrents of grim determination and hidden affection",
    "socialMask": "Capable, aggressive, no-nonsense authority figure who tolerates no weakness or excuses",
    "contradictions": [
      "Demands complete independence yet carries the weight of complete dependence on her",
      "Scorns emotional attachments while sacrificing everything for her crew's welfare",
      "Presents herself as purely pragmatic while making irrational decisions for loyalty",
      "Criticizes her crew for incompetence while defending them fiercely from outside judgment"
    ],
    "internalConflicts": [
      "Fear that she's wasted her talents on unworthy people versus fear of abandoning them",
      "Desire for legitimate success versus comfort with operating in moral grey areas",
      "Need for control versus frustration that control requires constant, exhausting vigilance",
      "Contempt for weakness versus self-awareness of her own emotional vulnerabilities"
    ],
    "wakeUpQuestions": [
      "Will today be the day one of them gets everyone killed?",
      "How much longer can I keep this together?",
      "Is there anyone in this world I can actually trust?",
      "What am I still fighting for?"
    ],
    "psychologicalProfile": {
      "attachmentStyle": "Dismissive-Avoidant with rare moments of anxious attachment to chosen family",
      "copingMechanisms": [
        "Physical violence and aggressive action",
        "Hypercontrol of situations and people",
        "Self-deprecating humor masking genuine pain",
        "Workaholism and constant motion",
        "Compartmentalization of emotional responses"
      ],
      "cognitiveBiases": [
        "Fundamental attribution error—assumes others' failures are character flaws rather than circumstance",
        "Overconfidence in her own abilities compensating for deep insecurity",
        "Confirmation bias—seeks evidence that people need her",
        "Catastrophic thinking during moments of vulnerability"
      ],
      "moralFramework": "Pragmatic utilitarianism with an undertone of street-level honor code. Does what's necessary, not what's legal. Protects her own above abstract principles. Has her own code that overrides formal law."
    },
    "conversationPersona": {
      "defaultTrust": 0.3,
      "trustEscalation": "Consistent competence, honesty under pressure, or demonstrated willingness to die for the crew",
      "informationRelease": "Shared danger, earned respect through actions, or when drunk (which is rare)",
      "deflectionPatterns": [
        "Redirects emotional questions to tactical concerns",
        "Uses aggressive humor to shut down vulnerability probes",
        "Dismisses compliments or personal observations",
        "Attacks the questioner's motives rather than answer sensitive questions"
      ]
    },
    "consciousWant": "Legitimate wealth and independence for herself and her crew, earned through skill and cunning",
    "unconsciousNeed": "To be needed and valued; to prove her worth through indispensability; to belong to something despite her fundamental belief she doesn't deserve it",
    "characterArc": {
      "summary": "From isolated survivalist to reluctant leader learning that her crew's competence isn't the point—their loyalty and growth is",
      "startState": "Viewing her crew as burdens to manage and problems to solve",
      "endState": "Accepting that she has built a family, and that family's worth isn't measured by their usefulness",
      "stages": [
        "Harsh command and constant criticism",
        "Moment of crisis where crew acts without her direction successfully",
        "Begrudging acknowledgment of their potential",
        "Realization that she's been protecting them because she loves them",
        "Shift from management to mentorship"
      ]
    },
    "opinionsAbout": {
      "fry_the_delivery_boy": "A bumbling fool who somehow has more innate capability than he realizes. Sees in him the potential for genuine growth—which terrifies and fascinates her. She's harder on him because she believes he could be more. Might actually be the crew member she secretly respects most, though she'd never admit it."
    }
  },
  "fallbackLines": {
    "player_addressed": [
      "State your business. I don't have time for pleasantries.",
      "You look like trouble. Are you the competent kind or the stupid kind?",
      "Whatever you're about to ask, the answer is probably no. But go ahead.",
      "I've got a ship to run and a crew of fools depending on me. Make it quick.",
      "You've got thirty seconds before I decide you're not worth the conversation.",
      "I've faced worse than you. Probably. Depends on how capable you actually are.",
      "Spit it out. Subtlety is wasted on people who can't follow direct orders."
    ],
    "idle": [
      "Another day, another series of preventable disasters.",
      "If I have to explain basic navigation one more time...",
      "The Consortium thinks they can pressure me. They have no idea what pressure actually is.",
      "This crew would be drowning in the harbor within a tenday without me.",
      "Sometimes I wonder what my life would be if I'd just taken that contract in the Sword Coasts instead.",
      "At least the ship's still floating. That's more than I can say for most of my plans.",
      "I need a drink. Or ten. Or to hit something. Preferably something that deserves it."
    ]
  }
}